djangocms_helpers/__init__.py
djangocms_helpers/admin.py
djangocms_helpers/apps.py
djangocms_helpers/receivers.py
djangocms_helpers/storage.py
djangocms_helpers/divio/__init__.py
djangocms_helpers/divio/management/__init__.py
djangocms_helpers/divio/management/commands/__init__.py
djangocms_helpers/divio/management/commands/aldryn_migrate.py
djangocms_helpers/divio/management/commands/aldryn_web.py
djangocms_helpers/fixes/__init__.py
djangocms_helpers/fixes/aldryn_sso_admin.py
djangocms_helpers/fixes/language_slug_fix.py
djangocms_helpers/management/__init__.py
djangocms_helpers/management/commands/__init__.py
djangocms_helpers/management/commands/create_cms_plugin.py
djangocms_helpers/management/commands/test_pages_on_real_db.py
djangocms_helpers/monkey_patches/__init__.py
djangocms_helpers/monkey_patches/static_placeholder_publishing_fix.py
djangocms_helpers/sentry_500_error_handler/__init__.py
djangocms_helpers/sentry_500_error_handler/ignore_io_error.py
djangocms_helpers/sentry_500_error_handler/views.py
djangocms_helpers/sentry_500_error_handler/templates/error_handler/404.html
djangocms_helpers/sentry_500_error_handler/templates/error_handler/500.html
djangocms_helpers/tests/__init__.py
djangocms_helpers/tests/test_pages.py
djangocms_helpers/utils/send_email.py
djangocms_helpers-2.2.2.0.dist-info/METADATA
djangocms_helpers-2.2.2.0.dist-info/WHEEL
djangocms_helpers-2.2.2.0.dist-info/top_level.txt
djangocms_helpers-2.2.2.0.dist-info/RECORD
