Metadata-Version: 2.1
Name: djangocms-helpers
Version: 2.2.2.0
Summary: A set of fixes, patches and utils for django-cms
Requires-Dist: django (<4,>=2.2)
Requires-Dist: django-fieldsignals (>=0.4.0)
Requires-Dist: django-meta
